{
    "0x00158d00024dec98": {
        "voltage": 3005,
        "battery": 100,
        "illuminance": 85,
        "illuminance_lux": 85,
        "temperature": 30,
        "occupancy": false,
        "device_temperature": 28,
        "linkquality": 255,
        "power_outage_count": 39,
        "last_seen": "2024-02-08T12:51:49+01:00"
    },
    "0x00158d0002760af1": {
        "voltage": 3005,
        "battery": 100,
        "illuminance": 10,
        "illuminance_lux": 10,
        "temperature": 24,
        "occupancy": false,
        "device_temperature": 18,
        "linkquality": 255,
        "power_outage_count": 28,
        "last_seen": "2024-02-08T12:53:38+01:00"
    },
    "0x00158d000249f36f": {
        "voltage": 2845,
        "battery": 0,
        "temperature": 21.73,
        "humidity": 48.17,
        "pressure": 1008.9,
        "linkquality": 239,
        "power_outage_count": 58108,
        "last_seen": "2024-02-08T12:16:54+01:00"
    },
    "0x00158d0002300b42": {
        "voltage": 2895,
        "battery": 30,
        "temperature": 19.93,
        "humidity": 61.8,
        "pressure": 992.7,
        "linkquality": 255,
        "power_outage_count": 68,
        "last_seen": "2024-02-08T11:05:02+01:00"
    },
    "0x14b457fffe7c2f46": {
        "battery": 34,
        "occupancy": false,
        "update": {
            "state": "idle",
            "installed_version": "2.0.022"
        },
        "update_available": false,
        "illuminance_above_threshold": false,
        "linkquality": 191,
        "last_seen": "2022-10-13T17:23:55+02:00"
    },
    "0x00158d0002302711": {
        "voltage": 3015,
        "battery": 100,
        "power_outage_count": 26964,
        "temperature": 20.27,
        "humidity": 56.49,
        "pressure": 1009,
        "last_seen": "2024-02-08T06:35:00+01:00",
        "linkquality": 247
    }
}